liungfu/__init__.py
liungfu/server.py
liungfu-0.1.0.dist-info/LICENSE
liungfu-0.1.0.dist-info/METADATA
liungfu-0.1.0.dist-info/WHEEL
liungfu-0.1.0.dist-info/entry_points.txt
liungfu-0.1.0.dist-info/top_level.txt
liungfu-0.1.0.dist-info/RECORD
