Metadata-Version: 2.1
Name: liungfu
Version: 0.1.0
Summary: permainan liungfu sederhana
Home-page: https://github.com/ExsoKamabay/ipwhois
Author: Exso Kamabay
License: Apache License 2.0
Keywords: kamabay,liungfu,judi,permainan,game
Platform: UNKNOWN
Classifier: License :: OSI Approved :: Apache Software License
Classifier: Operating System :: OS Independent
Classifier: Programming Language :: Python :: 3
Classifier: Topic :: Utilities
